{
	"configurations" : 
	[
		{
			"directories" : 
			[
				{
					"build" : ".",
					"childIndexes" : 
					[
						1
					],
					"jsonFile" : "directory-.-Debug-d0094a50bb2071803777.json",
					"minimumCMakeVersion" : 
					{
						"string" : "3.0.0"
					},
					"projectIndex" : 0,
					"source" : ".",
					"targetIndexes" : 
					[
						0
					]
				},
				{
					"build" : "lib",
					"jsonFile" : "directory-lib-Debug-e9069484d90298468a11.json",
					"minimumCMakeVersion" : 
					{
						"string" : "3.0.0"
					},
					"parentIndex" : 0,
					"projectIndex" : 0,
					"source" : "lib",
					"targetIndexes" : 
					[
						1
					]
				}
			],
			"name" : "Debug",
			"projects" : 
			[
				{
					"directoryIndexes" : 
					[
						0,
						1
					],
					"name" : "mp3",
					"targetIndexes" : 
					[
						0,
						1
					]
				}
			],
			"targets" : 
			[
				{
					"directoryIndex" : 0,
					"id" : "mp3::@6890427a1f51a3e7e1df",
					"jsonFile" : "target-mp3-Debug-d91b830c9ac39c54b7a0.json",
					"name" : "mp3",
					"projectIndex" : 0
				},
				{
					"directoryIndex" : 1,
					"id" : "parser::@306ed2d68c6501e8728f",
					"jsonFile" : "target-parser-Debug-171c4133222f0ba77c21.json",
					"name" : "parser",
					"projectIndex" : 0
				}
			]
		}
	],
	"kind" : "codemodel",
	"paths" : 
	{
		"build" : "D:/Desktop/pizh2322_malcev-week07_week16/labwork7/out/build/x64-Debug",
		"source" : "D:/Desktop/pizh2322_malcev-week07_week16/labwork7"
	},
	"version" : 
	{
		"major" : 2,
		"minor" : 5
	}
}
